DaikinInterface.py
README.md
setup.py
daikin_ha_wifi_control.egg-info/PKG-INFO
daikin_ha_wifi_control.egg-info/SOURCES.txt
daikin_ha_wifi_control.egg-info/dependency_links.txt
daikin_ha_wifi_control.egg-info/requires.txt
daikin_ha_wifi_control.egg-info/top_level.txt