Metadata-Version: 1.1
Name: daikin-ha-wifi-control
Version: 0.0.3
Summary: Classes for controlling Daikin AC and air purifiers over WLAN
Home-page: https://github.com/lmpprk/daikin_ha_wifi_control
Author: UNKNOWN
Author-email: UNKNOWN
License: UNKNOWN
Keywords: daikin homeautomation
Platform: UNKNOWN
Classifier: Development Status :: 3 - Alpha
Classifier: Intended Audience :: Developers
Classifier: Topic :: Home Automation
Classifier: License :: OSI Approved :: MIT License
Classifier: Programming Language :: Python :: 3.6
